audiojudge/__init__.py
audiojudge/api_cache.py
audiojudge/core.py
audiojudge/gemini_messages.py
audiojudge/openai_messages.py
audiojudge/utils.py
audiojudge/signal_audios/audio.wav
audiojudge/signal_audios/audio_1.wav
audiojudge/signal_audios/audio_2.wav
audiojudge/signal_audios/audio_response.wav
audiojudge/signal_audios/example_0.wav
audiojudge/signal_audios/example_1.wav
audiojudge/signal_audios/example_10.wav
audiojudge/signal_audios/example_2.wav
audiojudge/signal_audios/example_3.wav
audiojudge/signal_audios/example_4.wav
audiojudge/signal_audios/example_5.wav
audiojudge/signal_audios/example_6.wav
audiojudge/signal_audios/example_7.wav
audiojudge/signal_audios/example_8.wav
audiojudge/signal_audios/example_9.wav
audiojudge/signal_audios/first_audio.wav
audiojudge/signal_audios/instruction.wav
audiojudge/signal_audios/second_audio.wav
audiojudge/signal_audios/test.wav
audiojudge/signal_audios/test_audio.wav
audiojudge-0.1.2.data/data/audiojudge/signal_audios/audio.wav
audiojudge-0.1.2.data/data/audiojudge/signal_audios/audio_1.wav
audiojudge-0.1.2.data/data/audiojudge/signal_audios/audio_2.wav
audiojudge-0.1.2.data/data/audiojudge/signal_audios/audio_response.wav
audiojudge-0.1.2.data/data/audiojudge/signal_audios/example_0.wav
audiojudge-0.1.2.data/data/audiojudge/signal_audios/example_1.wav
audiojudge-0.1.2.data/data/audiojudge/signal_audios/example_10.wav
audiojudge-0.1.2.data/data/audiojudge/signal_audios/example_2.wav
audiojudge-0.1.2.data/data/audiojudge/signal_audios/example_3.wav
audiojudge-0.1.2.data/data/audiojudge/signal_audios/example_4.wav
audiojudge-0.1.2.data/data/audiojudge/signal_audios/example_5.wav
audiojudge-0.1.2.data/data/audiojudge/signal_audios/example_6.wav
audiojudge-0.1.2.data/data/audiojudge/signal_audios/example_7.wav
audiojudge-0.1.2.data/data/audiojudge/signal_audios/example_8.wav
audiojudge-0.1.2.data/data/audiojudge/signal_audios/example_9.wav
audiojudge-0.1.2.data/data/audiojudge/signal_audios/first_audio.wav
audiojudge-0.1.2.dist-info/METADATA
audiojudge-0.1.2.dist-info/WHEEL
audiojudge-0.1.2.dist-info/licenses/LICENSE
audiojudge-0.1.2.dist-info/RECORD
