Metadata-Version: 2.4
Name: audiojudge
Version: 0.1.2
Summary: A simple package for audio comparison using large language models
Project-URL: Homepage, https://github.com/woodygan/audiojudge
Project-URL: Repository, https://github.com/woodygan/audiojudge
Project-URL: Documentation, https://github.com/woodygan/audiojudge#readme
Project-URL: Bug Tracker, https://github.com/woodygan/audiojudge/issues
Project-URL: Changelog, https://github.com/woodygan/audiojudge/releases
Author-email: Woody Gan <woodygan@usc.edu>
License: MIT
License-File: LICENSE
Keywords: ai,audio,comparison,gemini,llm,openai,pronunciation,speech
Classifier: Development Status :: 3 - Alpha
Classifier: Intended Audience :: Developers
Classifier: Intended Audience :: Science/Research
Classifier: License :: OSI Approved :: MIT License
Classifier: Operating System :: OS Independent
Classifier: Programming Language :: Python :: 3
Classifier: Programming Language :: Python :: 3.10
Classifier: Programming Language :: Python :: 3.11
Classifier: Programming Language :: Python :: 3.12
Classifier: Programming Language :: Python :: 3.13
Classifier: Topic :: Multimedia :: Sound/Audio :: Analysis
Classifier: Topic :: Scientific/Engineering :: Artificial Intelligence
Classifier: Topic :: Software Development :: Libraries :: Python Modules
Requires-Python: >=3.10
Requires-Dist: audioop-lts>=0.2.1; python_version >= '3.13'
Requires-Dist: diskcache>=5.4.0
Requires-Dist: google-generativeai>=0.3.0
Requires-Dist: openai>=1.0.0
Requires-Dist: pydub>=0.25.1
Provides-Extra: dev
Requires-Dist: black>=22.0; extra == 'dev'
Requires-Dist: build>=0.8; extra == 'dev'
Requires-Dist: flake8>=4.0; extra == 'dev'
Requires-Dist: mypy>=0.991; extra == 'dev'
Requires-Dist: pytest>=6.0; extra == 'dev'
Requires-Dist: twine>=4.0; extra == 'dev'
